README.md
setup.py
pulumiverse_astra/__init__.py
pulumiverse_astra/_inputs.py
pulumiverse_astra/_utilities.py
pulumiverse_astra/access_list.py
pulumiverse_astra/cdc.py
pulumiverse_astra/database.py
pulumiverse_astra/get_access_list.py
pulumiverse_astra/get_astra_database.py
pulumiverse_astra/get_astra_databases.py
pulumiverse_astra/get_available_regions.py
pulumiverse_astra/get_keyspace.py
pulumiverse_astra/get_keyspaces.py
pulumiverse_astra/get_private_link_endpoints.py
pulumiverse_astra/get_private_links.py
pulumiverse_astra/get_role.py
pulumiverse_astra/get_roles.py
pulumiverse_astra/get_secure_connect_bundle_url.py
pulumiverse_astra/get_streaming_tenant_tokens.py
pulumiverse_astra/get_users.py
pulumiverse_astra/keyspace.py
pulumiverse_astra/outputs.py
pulumiverse_astra/private_link.py
pulumiverse_astra/private_link_endpoint.py
pulumiverse_astra/provider.py
pulumiverse_astra/pulumi-plugin.json
pulumiverse_astra/py.typed
pulumiverse_astra/role.py
pulumiverse_astra/streaming_sink.py
pulumiverse_astra/streaming_tenant.py
pulumiverse_astra/streaming_topic.py
pulumiverse_astra/table.py
pulumiverse_astra/token.py
pulumiverse_astra.egg-info/PKG-INFO
pulumiverse_astra.egg-info/SOURCES.txt
pulumiverse_astra.egg-info/dependency_links.txt
pulumiverse_astra.egg-info/not-zip-safe
pulumiverse_astra.egg-info/requires.txt
pulumiverse_astra.egg-info/top_level.txt
pulumiverse_astra/config/__init__.py
pulumiverse_astra/config/vars.py