Metadata-Version: 2.1
Name: pulumiverse-astra
Version: 1.0.39
Summary: A Pulumi package for creating and managing Astra DB cloud resources.
Home-page: https://www.pulumi.com
License: Apache-2.0
Project-URL: Repository, https://github.com/pulumiverse/pulumi-astra
Keywords: pulumi astra category/cloud datastax
Platform: UNKNOWN
